cihai_cli/__about__.py
cihai_cli/__init__.py
cihai_cli/_colors.py
cihai_cli/_formatter.py
cihai_cli/cli.py
cihai_cli/py.typed
cihai_cli-0.32.0.dist-info/METADATA
cihai_cli-0.32.0.dist-info/WHEEL
cihai_cli-0.32.0.dist-info/entry_points.txt
cihai_cli-0.32.0.dist-info/licenses/LICENSE
cihai_cli-0.32.0.dist-info/RECORD
