Metadata-Version: 2.4
Name: cihai-cli
Version: 0.32.0
Summary: Command line frontend for the cihai CJK language library
Project-URL: Bug Tracker, https://github.com/cihai/cihai-cli/issues
Project-URL: Documentation, https://cihai-cli.git-pull.com
Project-URL: Repository, https://github.com/cihai/cihai-cli
Project-URL: Release notes, https://github.com/cihai/cihai-cli/blob/master/CHANGES
Project-URL: Q & A, https://github.com/cihai/cihai-cli/discussions
Author-email: Tony Narlock <tony@git-pull.com>
License: MIT
License-File: LICENSE
Keywords: chinese,cjk,cli,dataset,dictionary,encyclopedia,japanese,korean,languages,library,shell,sqlalchemy,study,terminal,unicode,unihan
Classifier: Development Status :: 4 - Beta
Classifier: Environment :: Web Environment
Classifier: Intended Audience :: Developers
Classifier: License :: OSI Approved :: MIT License
Classifier: Programming Language :: Python
Classifier: Programming Language :: Python :: 3
Classifier: Programming Language :: Python :: 3.10
Classifier: Programming Language :: Python :: 3.11
Classifier: Programming Language :: Python :: 3.12
Classifier: Programming Language :: Python :: 3.13
Classifier: Programming Language :: Python :: 3.14
Classifier: Programming Language :: Python :: Implementation :: PyPy
Classifier: Topic :: Software Development :: Internationalization
Classifier: Topic :: Software Development :: Localization
Classifier: Topic :: System :: Shells
Classifier: Topic :: Utilities
Requires-Python: <4.0,>=3.10
Requires-Dist: cihai~=0.36.1
Requires-Dist: pyyaml
